aioservicethread/__init__.py
aioservicethread/aioservicethread.py
aioservicethread-0.2.0.dist-info/LICENSE
aioservicethread-0.2.0.dist-info/METADATA
aioservicethread-0.2.0.dist-info/WHEEL
aioservicethread-0.2.0.dist-info/top_level.txt
aioservicethread-0.2.0.dist-info/RECORD
